Metadata-Version: 2.1
Name: PrintDocx
Version: 0.1.1
Summary: Describe your package in one sentence
Home-page: https://github.com/you/your_package
Author: Paolo Mambrini
Author-email: you@email.com
License: Apache License 2.0
Platform: UNKNOWN
